__init__.py
mmi_constants/__init__.py
mmi_constants/laneConstants.py
mmi_constants/productConstants.py
mmi_constants/rootConstants.py
mmi_constants/routingConstants.py
mmi_constants/sharedConstants.py
mmi_core/laneDBMethods.py
mmi_core/productDBMethod.py
mmi_core/rootDBMethods.py
mmi_core/routingmainMethods.py
mmi_core/sharedDBMethod.py
mmi_dbConnections/__init__.py
mmi_dbConnections/postgresConnection.py
mmi_dbConnections/sqlConnection.py
mmi_dbMethods/__init__.py
mmi_dbMethods/commonFunctions.py
mmi_dbMethods/dbconfig.py
mmi_dbMethods/initDatabase.py
mmi_dbMethods/laneBoundaryTileTable.py
mmi_dbMethods/laneGeoTileTable.py
mmi_dbMethods/laneTileTable.py
mmi_dbMethods/modMethods.py
mmi_dbMethods/routingAuxTileTable.py
mmi_dbMethods/routingTileTable.py
mmi_functions/__init__.py
mmi_functions/conversionlib.py
mmi_functions/toCSV.py
mmi_nds-0.0.1.dist-info/LICENSE
mmi_nds-0.0.1.dist-info/METADATA
mmi_nds-0.0.1.dist-info/WHEEL
mmi_nds-0.0.1.dist-info/top_level.txt
mmi_nds-0.0.1.dist-info/RECORD
